Metadata-Version: 2.1
Name: pyfrontend
Version: 1.0.0
Summary: Make websites using Python
Home-page: https://github.com/sarmadgulzar/pyfrontend
Author: Sarmad Gulzar
Author-email: sarmadgulzar@outlook.com
License: MIT
Platform: UNKNOWN
Classifier: Programming Language :: Python :: 3
Classifier: License :: OSI Approved :: MIT License
Classifier: Operating System :: OS Independent
